{"gold_per_floor":[114,114,133,152,152],"floor_reached":5,"playtime":243,"items_purged":[],"score":31,"play_id":"19c4ab7f-a263-416a-a23a-96d36507ecca","local_time":"20190129085446","daily_mods":["Allstar","Flight","DeadlyEvents"],"is_ascension_mode":false,"campfire_choices":[],"neow_cost":"","seed_source_timestamp":0,"circlet_count":0,"master_deck":["Strike_R","Strike_R","Strike_R","Strike_R","Strike_R","Defend_R","Defend_R","Defend_R","Defend_R","Bash","Finesse","Madness","Master of Strategy","Enlightenment","Metamorphosis","Uppercut","Dropkick"],"special_seed":17925,"relics":["Burning Blood","Golden Idol"],"potions_floor_usage":[],"damage_taken":[{"damage":6,"enemies":"Jaw Worm","floor":1,"turns":3},{"damage":5,"enemies":"Small Slimes","floor":3,"turns":3},{"damage":7,"enemies":"2 Louse","floor":4,"turns":2}],"seed_played":"-7783971571703722258","potions_obtained":[{"floor":1,"key":"SpeedPotion"}],"is_trial":false,"path_per_floor":["M","?","M","M","$"],"character_chosen":"IRONCLAD","items_purchased":[],"campfire_rested":0,"item_purchase_floors":[],"current_hp_per_floor":[80,60,61,60,60],"gold":152,"neow_bonus":"","is_prod":false,"is_daily":true,"chose_seed":false,"campfire_upgraded":0,"win_rate":0,"timestamp":1548780886,"path_taken":["M","?","M","M","$"],"build_version":"2019-01-23","purchased_purges":0,"victory":false,"max_hp_per_floor":[80,80,80,80,80],"card_choices":[{"not_picked":["Corruption","Sentinel"],"picked":"Uppercut","floor":1},{"not_picked":["Body Slam","True Grit","Havoc"],"picked":"SKIP","floor":3},{"not_picked":["Cleave","Rampage"],"picked":"Dropkick","floor":4}],"player_experience":615084,"relics_obtained":[],"event_choices":[{"damage_healed":0,"gold_gain":0,"player_choice":"Take Damage","damage_taken":20,"relics_obtained":["Golden Idol"],"max_hp_gain":0,"max_hp_loss":0,"event_name":"Golden Idol","floor":2,"gold_loss":0}],"is_beta":false,"boss_relics":[],"items_purged_floors":[],"is_endless":false,"potions_floor_spawned":[1],"ascension_level":0}