{"gold_per_floor":[117,131,141,53,73,73,90,90],"floor_reached":8,"playtime":183,"items_purged":[],"score":100,"play_id":"85dd9238-519b-4ce9-8cac-7ceb15155a64","local_time":"20190222174928","is_ascension_mode":true,"campfire_choices":[{"data":"Hologram","floor":6,"key":"SMITH"}],"neow_cost":"NONE","seed_source_timestamp":424686497681967,"circlet_count":0,"master_deck":["AscendersBane","Strike_B","Strike_B","Strike_B","Strike_B","Defend_B","Defend_B","Defend_B","Defend_B","Zap","Dualcast","Hologram+1","BootSequence","Turbo","Capacitor","Double Energy","Streamline"],"relics":["Cracked Core","NeowsBlessing"],"potions_floor_usage":[8],"damage_taken":[{"damage":0,"enemies":"Cultist","floor":1,"turns":1},{"damage":0,"enemies":"2 Louse","floor":2,"turns":1},{"damage":0,"enemies":"Small Slimes","floor":3,"turns":1},{"damage":4,"enemies":"2 Fungi Beasts","floor":5,"turns":4},{"damage":20,"enemies":"Large Slime","floor":7,"turns":6},{"damage":67,"enemies":"Gremlin Nob","floor":8,"turns":4}],"seed_played":"372693460819438626","potions_obtained":[{"floor":3,"key":"AttackPotion"},{"floor":5,"key":"Ancient Potion"}],"is_trial":false,"path_per_floor":["M","M","M","$","M","R","M","E"],"character_chosen":"DEFECT","items_purchased":["Capacitor"],"campfire_rested":0,"item_purchase_floors":[4],"current_hp_per_floor":[64,64,64,64,60,60,40,0],"gold":90,"neow_bonus":"THREE_ENEMY_KILL","is_prod":false,"is_daily":false,"chose_seed":false,"campfire_upgraded":1,"win_rate":0,"timestamp":1550828968,"path_taken":["M","M","M","$","M","R","M","E"],"build_version":"2019-01-23","purchased_purges":0,"victory":false,"max_hp_per_floor":[71,71,71,71,71,71,71,71],"card_choices":[{"not_picked":["Leap","Fusion"],"picked":"Hologram","floor":1},{"not_picked":["Melter","Fusion"],"picked":"BootSequence","floor":2},{"not_picked":["Streamline","Hello World"],"picked":"Turbo","floor":3},{"not_picked":["Force Field","Chill"],"picked":"Double Energy","floor":5},{"not_picked":["Rebound","White Noise"],"picked":"Streamline","floor":7}],"player_experience":909249,"relics_obtained":[],"event_choices":[],"is_beta":false,"boss_relics":[],"items_purged_floors":[],"is_endless":false,"potions_floor_spawned":[3,5],"killed_by":"Gremlin Nob","ascension_level":20}