{"gold_per_floor":[99],"floor_reached":1,"playtime":71,"items_purged":[],"score":5,"play_id":"250bd7d4-3c98-4f22-a6fb-19cff485ecf3","local_time":"20190321023053","daily_mods":["Draft","Heirloom","Flight","DeadlyEvents"],"is_ascension_mode":false,"campfire_choices":[],"neow_cost":"","seed_source_timestamp":619429815645518,"circlet_count":0,"master_deck":["Armaments","Intimidate","Pommel Strike","Iron Wave","Clothesline","Searing Blow","Havoc","Corruption","Warcry","Inflame","Sword Boomerang","Flex","Whirlwind","Clash","Flex"],"relics":["Burning Blood","Turnip"],"potions_floor_usage":[],"damage_taken":[{"damage":4,"enemies":"Cultist","floor":1,"turns":3}],"seed_played":"-7619211134865540918","potions_obtained":[],"is_trial":true,"path_per_floor":["M"],"character_chosen":"IRONCLAD","items_purchased":[],"campfire_rested":0,"item_purchase_floors":[],"current_hp_per_floor":[76],"gold":99,"neow_bonus":"","is_prod":false,"is_daily":false,"chose_seed":false,"campfire_upgraded":0,"win_rate":0,"timestamp":1553103053,"path_taken":["M"],"build_version":"2019-01-23","purchased_purges":0,"victory":false,"max_hp_per_floor":[80],"card_choices":[{"not_picked":["Clash","Cleave"],"picked":"Armaments","floor":0},{"not_picked":["Heavy Blade","Anger"],"picked":"Intimidate","floor":0},{"not_picked":["Clothesline","Wild Strike"],"picked":"Pommel Strike","floor":0},{"not_picked":["Perfected Strike","Wild Strike"],"picked":"Iron Wave","floor":0},{"not_picked":["Armaments","Blood for Blood"],"picked":"Clothesline","floor":0},{"not_picked":["Clash","Iron Wave"],"picked":"Searing Blow","floor":0},{"not_picked":["Perfected Strike","Heavy Blade"],"picked":"Havoc","floor":0},{"not_picked":["Cleave","Warcry"],"picked":"Corruption","floor":0},{"not_picked":["Cleave","Fire Breathing"],"picked":"Warcry","floor":0},{"not_picked":["Body Slam","Thunderclap"],"picked":"Inflame","floor":0},{"not_picked":["True Grit","Clash"],"picked":"Sword Boomerang","floor":0},{"not_picked":["Clothesline","Seeing Red"],"picked":"Flex","floor":0},{"not_picked":["True Grit","Thunderclap"],"picked":"Whirlwind","floor":0},{"not_picked":["Heavy Blade","Dropkick"],"picked":"Clash","floor":0},{"not_picked":["Rampage","Body Slam"],"picked":"Flex","floor":0}],"player_experience":344594,"relics_obtained":[],"event_choices":[],"is_beta":false,"boss_relics":[],"items_purged_floors":[],"is_endless":true,"potions_floor_spawned":[],"killed_by":"Cultist","ascension_level":0}